django_pg_copy-1.3.0.dist-info/licenses/LICENSE
pg_copy/__init__.py
pg_copy/apps.py
pg_copy/settings.py
pg_copy/management/__init__.py
pg_copy/management/commands/__init__.py
pg_copy/management/commands/pg_backup.py
pg_copy/management/commands/pg_restore.py
pg_copy/migrations/__init__.py
django_pg_copy-1.3.0.dist-info/METADATA
django_pg_copy-1.3.0.dist-info/WHEEL
django_pg_copy-1.3.0.dist-info/top_level.txt
django_pg_copy-1.3.0.dist-info/RECORD
