Metadata-Version: 2.4
Name: django-pg-copy
Version: 1.3.0
Summary: Django management command to backup and restore PostgreSQL databases using the DATABASES settings.
Author-email: Tim Allen <tallen@wharton.upenn.edu>
License: BSD-3-Clause
Project-URL: Homepage, https://github.com/FlipperPA/django-pg-copy
Project-URL: Repository, https://github.com/FlipperPA/django-pg-copy
Project-URL: Documentation, https://github.com/FlipperPA/django-pg-copy
Keywords: postgres,postgresql,backup,restore,database
Classifier: Development Status :: 5 - Production/Stable
Classifier: Environment :: Web Environment
Classifier: Intended Audience :: Developers
Classifier: License :: OSI Approved :: BSD License
Classifier: Operating System :: OS Independent
Classifier: Programming Language :: Python :: 3
Classifier: Programming Language :: Python :: 3.7
Classifier: Programming Language :: Python :: 3.8
Classifier: Programming Language :: Python :: 3.9
Classifier: Programming Language :: Python :: 3.10
Classifier: Framework :: Django
Classifier: Topic :: Internet :: WWW/HTTP
Classifier: Topic :: Internet :: WWW/HTTP :: Dynamic Content
Requires-Python: >=3.7
License-File: LICENSE
Requires-Dist: Django
Requires-Dist: django-click
Provides-Extra: dev
Requires-Dist: ipython; extra == "dev"
Requires-Dist: ruff; extra == "dev"
Requires-Dist: pytest-coverage; extra == "dev"
Dynamic: license-file
